glide/__init__.py
glide/async_client.py
glide/exceptions.py
glide/lang/__init__.py
glide/lang/router_async.py
glide/lang/schemas.py
glide/logging.py
glide/py.typed
glide/schames.py
glide/testing/__init__.py
glide/typing.py
glide/version.py
glide_client-0.0.1a4.dist-info/METADATA
glide_client-0.0.1a4.dist-info/WHEEL
glide_client-0.0.1a4.dist-info/licenses/LICENSE
glide_client-0.0.1a4.dist-info/RECORD
