Metadata-Version: 2.1
Name: glide-client
Version: 0.0.1a4
Summary: An official Python client for Glide, an open resilient fast model gateway
Keywords: llm,llmops,gateway,infrastructure
Author-Email: Roman Hlushko <roman@einstack.ai>
License: Apache-2.0
Project-URL: Homepage, https://glide.einstack.ai/
Project-URL: Documentation, https://glide.einstack.ai/
Project-URL: Repository, https://github.com/me/spam.git
Project-URL: Issues, https://github.com/EinStack/glide-python
Requires-Python: >=3.8
Requires-Dist: httpx>=0.26.0
Requires-Dist: websockets>=12.0
Requires-Dist: pydantic>=2.6.1
